{"Origen":{"0":"Laborum","1":"Laborum","2":"Laborum","3":"Laborum","4":"Laborum","5":"Laborum","6":"Laborum","7":"Laborum","8":"Laborum","9":"Laborum","10":"Laborum","11":"Laborum","12":"Laborum","13":"Laborum","14":"Laborum","15":"Laborum","16":"Laborum","17":"Laborum","18":"Laborum","19":"Laborum","20":"Laborum","21":"Laborum","22":"Laborum","23":"Laborum","24":"Laborum","25":"Laborum","26":"Laborum","27":"Laborum","28":"Laborum","29":"Laborum","30":"Laborum","31":"Laborum","32":"Laborum","33":"Laborum","34":"Laborum","35":"Laborum","36":"Laborum","37":"Laborum","38":"Laborum","39":"Laborum","40":"Laborum","41":"Laborum","42":"Laborum","43":"Laborum","44":"Laborum","45":"Laborum","46":"Laborum","47":"Laborum","48":"Laborum","49":"Laborum","50":"Laborum","51":"Laborum","52":"Laborum","53":"Laborum","54":"Laborum","55":"Laborum","56":"Laborum","57":"Laborum","58":"Laborum","59":"Laborum","60":"Laborum","61":"Laborum","62":"Laborum","63":"Laborum","64":"Laborum","65":"Laborum","66":"Laborum","67":"Laborum","68":"Laborum","69":"Laborum","70":"Laborum","71":"Laborum","72":"Laborum","73":"Laborum","74":"Laborum","75":"Laborum","76":"Laborum","77":"Laborum","78":"Laborum","79":"Laborum","80":"Laborum","81":"Laborum","82":"Laborum","83":"Laborum","84":"Laborum","85":"Laborum","86":"Laborum","87":"Laborum","88":"Laborum","89":"Laborum","90":"Laborum","91":"Laborum","92":"Laborum","93":"Laborum","94":"Laborum","95":"Laborum","96":"Laborum","97":"Laborum","98":"Laborum","99":"Laborum","100":"Laborum","101":"Laborum","102":"Laborum","103":"Laborum","104":"Laborum","105":"Laborum","106":"Laborum","107":"Laborum","108":"Laborum","109":"Laborum","110":"Laborum","111":"Laborum","112":"Laborum","113":"Laborum","114":"Laborum","115":"Laborum","116":"Laborum","117":"Laborum","118":"Laborum","119":"Laborum","120":"Laborum","121":"Laborum","122":"Laborum","123":"Laborum","124":"Laborum","125":"Laborum","126":"Laborum","127":"Laborum","128":"Chiletrabajos2","129":"Chiletrabajos2","130":"Chiletrabajos2","131":"Chiletrabajos2","132":"Chiletrabajos2","133":"Chiletrabajos2","134":"Chiletrabajos2","135":"Chiletrabajos2","136":"Chiletrabajos2","137":"Chiletrabajos2","138":"Chiletrabajos2","139":"Chiletrabajos2","140":"Chiletrabajos2","141":"Chiletrabajos2","142":"Chiletrabajos2","143":"Chiletrabajos2","144":"Chiletrabajos2","145":"Chiletrabajos2","146":"Chiletrabajos2","147":"Chiletrabajos2","148":"Chiletrabajos2","149":"Chiletrabajos2","150":"Chiletrabajos2","151":"Chiletrabajos2","152":"Chiletrabajos2","153":"Chiletrabajos2","154":"Chiletrabajos2","155":"Chiletrabajos2","156":"Chiletrabajos2","157":"Chiletrabajos2","158":"Chiletrabajos2","159":"Chiletrabajos2","160":"Chiletrabajos2","161":"Chiletrabajos2","162":"Chiletrabajos2","163":"Chiletrabajos2","164":"Chiletrabajos2","165":"Chiletrabajos2","166":"Chiletrabajos2","167":"Chiletrabajos2","168":"Chiletrabajos2","169":"Chiletrabajos2","170":"Chiletrabajos2","171":"Chiletrabajos2","172":"Chiletrabajos2","173":"Chiletrabajos2","174":"Chiletrabajos2","175":"Chiletrabajos2","176":"Chiletrabajos2","177":"Chiletrabajos2","178":"Chiletrabajos2","179":"Chiletrabajos2","180":"Chiletrabajos2","181":"Bolsa Nacional de Empleo","182":"Bolsa Nacional de Empleo","183":"Bolsa Nacional de Empleo","184":"Bolsa Nacional de Empleo","185":"Bolsa Nacional de Empleo","186":"Bolsa Nacional de Empleo","187":"Bolsa Nacional de Empleo","188":"Bolsa Nacional de Empleo","189":"Bolsa Nacional de Empleo","190":"Bolsa Nacional de Empleo","191":"Bolsa Nacional de Empleo","192":"Bolsa Nacional de Empleo","193":"Bolsa Nacional de Empleo","194":"Bolsa Nacional de Empleo","195":"Bolsa Nacional de Empleo","196":"Chiletrabajos2","197":"Chiletrabajos2","198":"Chiletrabajos2","199":"Chiletrabajos2","200":"Chiletrabajos2","201":"Chiletrabajos2","202":"Chiletrabajos2","203":"Chiletrabajos2","204":"Chiletrabajos2","205":"Chiletrabajos2","206":"Chiletrabajos2","207":"Chiletrabajos2","208":"Chiletrabajos2","209":"Chiletrabajos2","210":"Chiletrabajos2","211":"Chiletrabajos2","212":"Laborum","213":"Laborum","214":"Laborum","215":"Laborum","216":"Laborum","217":"Laborum","218":"Laborum","219":"Laborum","220":"Laborum","221":"Laborum","222":"Laborum","223":"Laborum","224":"Laborum","225":"Laborum","226":"Laborum","227":"Laborum","228":"Laborum","229":"Laborum","230":"Laborum","231":"Laborum+ChileTrabajos+Bne","232":"Laborum+ChileTrabajos+Bne","233":"Laborum+ChileTrabajos+Bne","234":"Laborum+ChileTrabajos+Bne","235":"Laborum+ChileTrabajos+Bne","236":"Laborum+ChileTrabajos+Bne","237":"Laborum+ChileTrabajos+Bne","238":"Laborum+ChileTrabajos+Bne","239":"Laborum+ChileTrabajos+Bne","240":"Laborum+ChileTrabajos+Bne","241":"Laborum+ChileTrabajos+Bne","242":"Laborum+ChileTrabajos+Bne","243":"Laborum+ChileTrabajos+Bne","244":"Laborum+ChileTrabajos+Bne","245":"Laborum+ChileTrabajos+Bne","246":"Laborum+ChileTrabajos+Bne","247":"Laborum+ChileTrabajos+Bne","248":"Laborum+ChileTrabajos+Bne","249":"Laborum+ChileTrabajos+Bne","250":"Laborum+ChileTrabajos+Bne","251":"Laborum+ChileTrabajos+Bne","252":"Laborum+ChileTrabajos+Bne","253":"Laborum+ChileTrabajos+Bne","254":"Laborum+ChileTrabajos+Bne","255":"Laborum+ChileTrabajos+Bne","256":"Laborum+ChileTrabajos+Bne","257":"Laborum+ChileTrabajos+Bne","258":"Laborum+ChileTrabajos+Bne","259":"Laborum+ChileTrabajos+Bne","260":"Laborum+ChileTrabajos+Bne","261":"Laborum+ChileTrabajos+Bne","262":"Laborum+ChileTrabajos+Bne","263":"Laborum+ChileTrabajos+Bne","264":"Laborum+ChileTrabajos+Bne","265":"Laborum+ChileTrabajos+Bne","266":"Laborum+ChileTrabajos+Bne","267":"Laborum+ChileTrabajos+Bne","268":"Laborum+ChileTrabajos+Bne","269":"Laborum+ChileTrabajos+Bne","270":"Laborum+ChileTrabajos+Bne","271":"Laborum+ChileTrabajos+Bne","272":"Laborum+ChileTrabajos+Bne","273":"Laborum+ChileTrabajos+Bne","274":"Laborum+ChileTrabajos+Bne","275":"Laborum+ChileTrabajos+Bne","276":"Laborum+ChileTrabajos+Bne","277":"Laborum+ChileTrabajos+Bne","278":"Laborum+ChileTrabajos+Bne","279":"Laborum+ChileTrabajos+Bne","280":"Laborum+ChileTrabajos+Bne","281":"Laborum+ChileTrabajos+Bne","282":"Laborum+ChileTrabajos+Bne","283":"Laborum+ChileTrabajos+Bne","284":"Laborum+ChileTrabajos+Bne","285":"Laborum+ChileTrabajos+Bne","286":"Laborum+ChileTrabajos+Bne","287":"Laborum+ChileTrabajos+Bne","288":"Laborum+ChileTrabajos+Bne","289":"Laborum+ChileTrabajos+Bne","290":"Laborum+ChileTrabajos+Bne","291":"Laborum+ChileTrabajos+Bne","292":"Laborum+ChileTrabajos+Bne","293":"Laborum+ChileTrabajos+Bne","294":"Laborum+ChileTrabajos+Bne","295":"Laborum+ChileTrabajos+Bne","296":"Laborum+ChileTrabajos+Bne","297":"Laborum+ChileTrabajos+Bne","298":"Laborum+ChileTrabajos+Bne","299":"Laborum+ChileTrabajos+Bne","300":"Laborum+ChileTrabajos+Bne","301":"Laborum+ChileTrabajos+Bne","302":"Laborum+ChileTrabajos+Bne","303":"Laborum+ChileTrabajos+Bne","304":"Laborum+ChileTrabajos+Bne","305":"Laborum+ChileTrabajos+Bne","306":"Laborum+ChileTrabajos+Bne","307":"Laborum+ChileTrabajos+Bne","308":"Laborum+ChileTrabajos+Bne","309":"Laborum+ChileTrabajos+Bne","310":"Laborum+ChileTrabajos+Bne","311":"Laborum+ChileTrabajos+Bne","312":"Laborum+ChileTrabajos+Bne","313":"Laborum+ChileTrabajos+Bne","314":"Laborum+ChileTrabajos+Bne","315":"Laborum+ChileTrabajos+Bne","316":"Laborum+ChileTrabajos+Bne","317":"Laborum+ChileTrabajos+Bne","318":"Laborum+ChileTrabajos+Bne","319":"Laborum+ChileTrabajos+Bne","320":"Laborum+ChileTrabajos+Bne","321":"Laborum+ChileTrabajos+Bne","322":"Laborum+ChileTrabajos+Bne","323":"Laborum+ChileTrabajos+Bne","324":"Laborum+ChileTrabajos+Bne","325":"Laborum+ChileTrabajos+Bne","326":"Laborum+ChileTrabajos+Bne","327":"Laborum+ChileTrabajos+Bne","328":"Laborum+ChileTrabajos+Bne","329":"Laborum+ChileTrabajos+Bne","330":"Laborum+ChileTrabajos+Bne","331":"Laborum+ChileTrabajos+Bne","332":"Laborum+ChileTrabajos+Bne","333":"Laborum+ChileTrabajos+Bne","334":"Laborum+ChileTrabajos+Bne","335":"Laborum+ChileTrabajos+Bne","336":"Laborum+ChileTrabajos+Bne","337":"Laborum+ChileTrabajos+Bne","338":"Laborum+ChileTrabajos+Bne","339":"Laborum+ChileTrabajos+Bne","340":"Laborum+ChileTrabajos+Bne","341":"Laborum+ChileTrabajos+Bne","342":"Laborum+ChileTrabajos+Bne","343":"Laborum+ChileTrabajos+Bne","344":"Laborum+ChileTrabajos+Bne","345":"Laborum+ChileTrabajos+Bne","346":"Laborum+ChileTrabajos+Bne","347":"Laborum+ChileTrabajos+Bne","348":"Laborum+ChileTrabajos+Bne","349":"Laborum+ChileTrabajos+Bne","350":"Laborum+ChileTrabajos+Bne","351":"Laborum+ChileTrabajos+Bne","352":"Laborum+ChileTrabajos+Bne","353":"Laborum+ChileTrabajos+Bne","354":"Laborum+ChileTrabajos+Bne","355":"Laborum+ChileTrabajos+Bne","356":"Laborum+ChileTrabajos+Bne","357":"Laborum+ChileTrabajos+Bne","358":"Laborum+ChileTrabajos+Bne","359":"Laborum+ChileTrabajos+Bne","360":"Laborum+ChileTrabajos+Bne","361":"Laborum+ChileTrabajos+Bne","362":"Laborum+ChileTrabajos+Bne","363":"Laborum+ChileTrabajos+Bne","364":"Laborum+ChileTrabajos+Bne","365":"Laborum+ChileTrabajos+Bne","366":"Laborum+ChileTrabajos+Bne","367":"Laborum+ChileTrabajos+Bne","368":"Laborum+ChileTrabajos+Bne","369":"Laborum+ChileTrabajos+Bne","370":"Laborum+ChileTrabajos+Bne","371":"Laborum+ChileTrabajos+Bne","372":"Laborum+ChileTrabajos+Bne","373":"Laborum+ChileTrabajos+Bne","374":"Laborum+ChileTrabajos+Bne","375":"Laborum+ChileTrabajos+Bne","376":"Laborum+ChileTrabajos+Bne","377":"Laborum+ChileTrabajos+Bne","378":"Laborum+ChileTrabajos+Bne","379":"Laborum+ChileTrabajos+Bne","380":"Laborum+ChileTrabajos+Bne","381":"Laborum+ChileTrabajos+Bne","382":"Laborum+ChileTrabajos+Bne","383":"Laborum+ChileTrabajos+Bne","384":"Laborum+ChileTrabajos+Bne","385":"Laborum+ChileTrabajos+Bne","386":"Laborum+ChileTrabajos+Bne","387":"Laborum+ChileTrabajos+Bne","388":"Laborum+ChileTrabajos+Bne","389":"Laborum+ChileTrabajos+Bne","390":"Laborum+ChileTrabajos+Bne","391":"Laborum+ChileTrabajos+Bne","392":"Laborum+ChileTrabajos+Bne","393":"Laborum+ChileTrabajos+Bne","394":"Laborum+ChileTrabajos+Bne","395":"Bolsa Nacional de Empleo","396":"Bolsa Nacional de Empleo","397":"Bolsa Nacional de Empleo","398":"Bolsa Nacional de Empleo","399":"Bolsa Nacional de Empleo","400":"Bolsa Nacional de Empleo","401":"Chiletrabajos2","402":"Chiletrabajos2","403":"Chiletrabajos2","404":"Chiletrabajos2","405":"Chiletrabajos2","406":"Chiletrabajos2","407":"Chiletrabajos2","408":"Chiletrabajos2","409":"Chiletrabajos2","410":"Chiletrabajos2","411":"Chiletrabajos2","412":"Chiletrabajos2","413":"Chiletrabajos2","414":"Chiletrabajos2","415":"Chiletrabajos2","416":"Chiletrabajos2","417":"Laborum","418":"Laborum","419":"Laborum","420":"Laborum","421":"Laborum","422":"Laborum","423":"Laborum","424":"Laborum","425":"Laborum","426":"Laborum","427":"Laborum","428":"Laborum","429":"Laborum","430":"Laborum","431":"Laborum","432":"Laborum","433":"Laborum","434":"Bolsa Nacional de Empleo","435":"Chiletrabajos2","436":"Laborum","437":"Laborum+ChileTrabajos+Bne"},"Region":{"0":"Antofagasta","1":"Antofagasta","2":"Antofagasta","3":"Antofagasta","4":"Antofagasta","5":"Antofagasta","6":"Antofagasta","7":"Antofagasta","8":"Arica y Parinacota","9":"Arica y Parinacota","10":"Arica y Parinacota","11":"Arica y Parinacota","12":"Atacama","13":"Atacama","14":"Atacama","15":"Atacama","16":"Atacama","17":"Atacama","18":"Atacama","19":"Atacama","20":"Atacama","21":"Atacama","22":"Atacama","23":"Aysen","24":"Aysen","25":"Aysen","26":"Bio Bio","27":"Bio Bio","28":"Bio Bio","29":"Bio Bio","30":"Bio Bio","31":"Coquimbo","32":"Coquimbo","33":"Coquimbo","34":"Coquimbo","35":"La Araucania","36":"La Araucania","37":"La Araucania","38":"La Araucania","39":"La Araucania","40":"La Araucania","41":"Los Lagos","42":"Los Lagos","43":"Los Lagos","44":"Los Lagos","45":"Los Lagos","46":"Los Lagos","47":"Los Lagos","48":"Los Lagos","49":"Los Rios","50":"Los Rios","51":"Los Rios","52":"Los Rios","53":"Los Rios","54":"Magallanes y Antartica Chilena","55":"Magallanes y Antartica Chilena","56":"Magallanes y Antartica Chilena","57":"Magallanes y Antartica Chilena","58":"Maule","59":"Maule","60":"Maule","61":"Maule","62":"Maule","63":"Maule","64":"Metropolitana","65":"Metropolitana","66":"Metropolitana","67":"Metropolitana","68":"Metropolitana","69":"Metropolitana","70":"Metropolitana","71":"Metropolitana","72":"Metropolitana","73":"Metropolitana","74":"Metropolitana","75":"Metropolitana","76":"Metropolitana","77":"Metropolitana","78":"Metropolitana","79":"Metropolitana","80":"Metropolitana","81":"Metropolitana","82":"Metropolitana","83":"O'Higgins","84":"O'Higgins","85":"O'Higgins","86":"O'Higgins","87":"O'Higgins","88":"O'Higgins","89":"O'Higgins","90":"O'Higgins","91":"Otros","92":"Otros","93":"Otros","94":"Otros","95":"Otros","96":"Otros","97":"Otros","98":"Otros","99":"Otros","100":"Otros","101":"Otros","102":"Otros","103":"Otros","104":"Otros","105":"Otros","106":"Otros","107":"Otros","108":"Otros","109":"Tarapaca","110":"Tarapaca","111":"Tarapaca","112":"Tarapaca","113":"Tarapaca","114":"Valparaiso","115":"Valparaiso","116":"Valparaiso","117":"Valparaiso","118":"Valparaiso","119":"Valparaiso","120":"Valparaiso","121":"Valparaiso","122":"Valparaiso","123":"\u00d1uble","124":"\u00d1uble","125":"\u00d1uble","126":"\u00d1uble","127":"\u00d1uble","128":"Antofagasta","129":"Antofagasta","130":"Antofagasta","131":"Antofagasta","132":"Antofagasta","133":"Antofagasta","134":"Arica y Parinacota","135":"Atacama","136":"Atacama","137":"Aysen","138":"Bio Bio","139":"Bio Bio","140":"Bio Bio","141":"Coquimbo","142":"La Araucania","143":"La Araucania","144":"Los Lagos","145":"Los Lagos","146":"Los Lagos","147":"Los Lagos","148":"Los Lagos","149":"Los Rios","150":"Maule","151":"Maule","152":"Maule","153":"Maule","154":"Metropolitana","155":"Metropolitana","156":"Metropolitana","157":"Metropolitana","158":"Metropolitana","159":"Metropolitana","160":"Metropolitana","161":"Metropolitana","162":"Metropolitana","163":"Metropolitana","164":"Metropolitana","165":"Metropolitana","166":"Metropolitana","167":"Metropolitana","168":"Metropolitana","169":"O'Higgins","170":"O'Higgins","171":"O'Higgins","172":"O'Higgins","173":"Otros","174":"Tarapaca","175":"Tarapaca","176":"Valparaiso","177":"Valparaiso","178":"Valparaiso","179":"\u00d1uble","180":"\u00d1uble","181":"Arica y Parinacota","182":"Bio Bio","183":"Maule","184":"Maule","185":"Metropolitana","186":"Metropolitana","187":"O'Higgins","188":"O'Higgins","189":"Tarapaca","190":"Chile","191":"Chile","192":"Chile","193":"Chile","194":"Chile","195":"Chile","196":"Chile","197":"Chile","198":"Chile","199":"Chile","200":"Chile","201":"Chile","202":"Chile","203":"Chile","204":"Chile","205":"Chile","206":"Chile","207":"Chile","208":"Chile","209":"Chile","210":"Chile","211":"Chile","212":"Chile","213":"Chile","214":"Chile","215":"Chile","216":"Chile","217":"Chile","218":"Chile","219":"Chile","220":"Chile","221":"Chile","222":"Chile","223":"Chile","224":"Chile","225":"Chile","226":"Chile","227":"Chile","228":"Chile","229":"Chile","230":"Chile","231":"Antofagasta","232":"Antofagasta","233":"Antofagasta","234":"Antofagasta","235":"Antofagasta","236":"Antofagasta","237":"Antofagasta","238":"Antofagasta","239":"Antofagasta","240":"Antofagasta","241":"Arica y Parinacota","242":"Arica y Parinacota","243":"Arica y Parinacota","244":"Arica y Parinacota","245":"Atacama","246":"Atacama","247":"Atacama","248":"Atacama","249":"Atacama","250":"Atacama","251":"Atacama","252":"Atacama","253":"Atacama","254":"Atacama","255":"Atacama","256":"Aysen","257":"Aysen","258":"Aysen","259":"Bio Bio","260":"Bio Bio","261":"Bio Bio","262":"Bio Bio","263":"Bio Bio","264":"Bio Bio","265":"Bio Bio","266":"Coquimbo","267":"Coquimbo","268":"Coquimbo","269":"Coquimbo","270":"Coquimbo","271":"La Araucania","272":"La Araucania","273":"La Araucania","274":"La Araucania","275":"La Araucania","276":"La Araucania","277":"La Araucania","278":"Los Lagos","279":"Los Lagos","280":"Los Lagos","281":"Los Lagos","282":"Los Lagos","283":"Los Lagos","284":"Los Lagos","285":"Los Lagos","286":"Los Lagos","287":"Los Rios","288":"Los Rios","289":"Los Rios","290":"Los Rios","291":"Los Rios","292":"Los Rios","293":"Magallanes y Antartica Chilena","294":"Magallanes y Antartica Chilena","295":"Magallanes y Antartica Chilena","296":"Magallanes y Antartica Chilena","297":"Maule","298":"Maule","299":"Maule","300":"Maule","301":"Maule","302":"Maule","303":"Maule","304":"Maule","305":"Metropolitana","306":"Metropolitana","307":"Metropolitana","308":"Metropolitana","309":"Metropolitana","310":"Metropolitana","311":"Metropolitana","312":"Metropolitana","313":"Metropolitana","314":"Metropolitana","315":"Metropolitana","316":"Metropolitana","317":"Metropolitana","318":"Metropolitana","319":"Metropolitana","320":"Metropolitana","321":"Metropolitana","322":"Metropolitana","323":"Metropolitana","324":"Metropolitana","325":"O'Higgins","326":"O'Higgins","327":"O'Higgins","328":"O'Higgins","329":"O'Higgins","330":"O'Higgins","331":"O'Higgins","332":"O'Higgins","333":"O'Higgins","334":"O'Higgins","335":"Otros","336":"Otros","337":"Otros","338":"Otros","339":"Otros","340":"Otros","341":"Otros","342":"Otros","343":"Otros","344":"Otros","345":"Otros","346":"Otros","347":"Otros","348":"Otros","349":"Otros","350":"Otros","351":"Otros","352":"Otros","353":"Tarapaca","354":"Tarapaca","355":"Tarapaca","356":"Tarapaca","357":"Tarapaca","358":"Tarapaca","359":"Tarapaca","360":"Valparaiso","361":"Valparaiso","362":"Valparaiso","363":"Valparaiso","364":"Valparaiso","365":"Valparaiso","366":"Valparaiso","367":"Valparaiso","368":"Valparaiso","369":"Valparaiso","370":"\u00d1uble","371":"\u00d1uble","372":"\u00d1uble","373":"\u00d1uble","374":"\u00d1uble","375":"Chile","376":"Chile","377":"Chile","378":"Chile","379":"Chile","380":"Chile","381":"Chile","382":"Chile","383":"Chile","384":"Chile","385":"Chile","386":"Chile","387":"Chile","388":"Chile","389":"Chile","390":"Chile","391":"Chile","392":"Chile","393":"Chile","394":"Chile","395":"Arica y Parinacota","396":"Bio Bio","397":"Maule","398":"Metropolitana","399":"O'Higgins","400":"Tarapaca","401":"Antofagasta","402":"Arica y Parinacota","403":"Atacama","404":"Aysen","405":"Bio Bio","406":"Coquimbo","407":"La Araucania","408":"Los Lagos","409":"Los Rios","410":"Maule","411":"Metropolitana","412":"O'Higgins","413":"Otros","414":"Tarapaca","415":"Valparaiso","416":"\u00d1uble","417":"Antofagasta","418":"Arica y Parinacota","419":"Atacama","420":"Aysen","421":"Bio Bio","422":"Coquimbo","423":"La Araucania","424":"Los Lagos","425":"Los Rios","426":"Magallanes y Antartica Chilena","427":"Maule","428":"Metropolitana","429":"O'Higgins","430":"Otros","431":"Tarapaca","432":"Valparaiso","433":"\u00d1uble","434":"Chile","435":"Chile","436":"Chile","437":"Chile"},"Categoria":{"0":"Administracion","1":"Economia \/ Contabilidad","2":"Informatica \/ Telecomunicaciones","3":"Marketing y Publicidad","4":"Medicina \/ Salud","5":"Operarios y no Profesionales","6":"Profesionales y Tecnicos","7":"Ventas \/ Comercial","8":"Administracion","9":"Medicina \/ Salud","10":"Recepci\u00f3n \/ Secretaria","11":"Ventas \/ Comercial","12":"Administracion","13":"Asistente administrativo","14":"Educacion y Psicopedagogia","15":"Hoteleria Turismo y Gastronomia","16":"Informatica \/ Telecomunicaciones","17":"Logistica \/ Distribucion","18":"Medicina \/ Salud","19":"Otros","20":"Profesionales y Tecnicos","21":"Recursos Humanos","22":"Ventas \/ Comercial","23":"Administracion","24":"Medicina \/ Salud","25":"Ventas \/ Comercial","26":"Economia \/ Contabilidad","27":"Medicina \/ Salud","28":"Profesionales y Tecnicos","29":"Recursos Humanos","30":"Ventas \/ Comercial","31":"Administracion","32":"Economia \/ Contabilidad","33":"Logistica \/ Distribucion","34":"Ventas \/ Comercial","35":"Economia \/ Contabilidad","36":"Logistica \/ Distribucion","37":"Otros","38":"Practicas profesionales","39":"Recursos Humanos","40":"Ventas \/ Comercial","41":"Administracion","42":"Economia \/ Contabilidad","43":"Logistica \/ Distribucion","44":"Medicina \/ Salud","45":"Otros","46":"Profesionales y Tecnicos","47":"Seguridad","48":"Ventas \/ Comercial","49":"Economia \/ Contabilidad","50":"Informatica \/ Telecomunicaciones","51":"Logistica \/ Distribucion","52":"Medicina \/ Salud","53":"Ventas \/ Comercial","54":"Economia \/ Contabilidad","55":"Logistica \/ Distribucion","56":"Medicina \/ Salud","57":"Ventas \/ Comercial","58":"Administracion","59":"Economia \/ Contabilidad","60":"Logistica \/ Distribucion","61":"Medicina \/ Salud","62":"Profesionales y Tecnicos","63":"Ventas \/ Comercial","64":"Administracion","65":"Arte\/Diseno\/Medios","66":"Asistente administrativo","67":"Economia \/ Contabilidad","68":"Educacion y Psicopedagogia","69":"Estetica y Cuidado Personal","70":"Hoteleria Turismo y Gastronomia","71":"Informatica \/ Telecomunicaciones","72":"Logistica \/ Distribucion","73":"Marketing y Publicidad","74":"Medicina \/ Salud","75":"Operarios y no Profesionales","76":"Otros","77":"Practicas profesionales","78":"Profesionales y Tecnicos","79":"Recepci\u00f3n \/ Secretaria","80":"Recursos Humanos","81":"Seguridad","82":"Ventas \/ Comercial","83":"Administracion","84":"Asistente administrativo","85":"Economia \/ Contabilidad","86":"Logistica \/ Distribucion","87":"Medicina \/ Salud","88":"Profesionales y Tecnicos","89":"Seguridad","90":"Ventas \/ Comercial","91":"Administracion","92":"Arte\/Diseno\/Medios","93":"Asistente administrativo","94":"Economia \/ Contabilidad","95":"Educacion y Psicopedagogia","96":"Estetica y Cuidado Personal","97":"Hoteleria Turismo y Gastronomia","98":"Informatica \/ Telecomunicaciones","99":"Logistica \/ Distribucion","100":"Marketing y Publicidad","101":"Medicina \/ Salud","102":"Operarios y no Profesionales","103":"Otros","104":"Practicas profesionales","105":"Profesionales y Tecnicos","106":"Recursos Humanos","107":"Seguridad","108":"Ventas \/ Comercial","109":"Administracion","110":"Economia \/ Contabilidad","111":"Logistica \/ Distribucion","112":"Medicina \/ Salud","113":"Ventas \/ Comercial","114":"Administracion","115":"Asistente administrativo","116":"Economia \/ Contabilidad","117":"Logistica \/ Distribucion","118":"Medicina \/ Salud","119":"Operarios y no Profesionales","120":"Profesionales y Tecnicos","121":"Seguridad","122":"Ventas \/ Comercial","123":"Economia \/ Contabilidad","124":"Logistica \/ Distribucion","125":"Medicina \/ Salud","126":"Operarios y no Profesionales","127":"Ventas \/ Comercial","128":"Asistente administrativo","129":"Informatica \/ Telecomunicaciones","130":"Medicina \/ Salud","131":"Operarios y no Profesionales","132":"Otros","133":"Profesionales y Tecnicos","134":"Medicina \/ Salud","135":"Otros","136":"Profesionales y Tecnicos","137":"Ventas \/ Comercial","138":"Economia \/ Contabilidad","139":"Otros","140":"Profesionales y Tecnicos","141":"Educacion y Psicopedagogia","142":"Profesionales y Tecnicos","143":"Ventas \/ Comercial","144":"Medicina \/ Salud","145":"Otros","146":"Profesionales y Tecnicos","147":"Recursos Humanos","148":"Ventas \/ Comercial","149":"Administracion","150":"Operarios y no Profesionales","151":"Profesionales y Tecnicos","152":"Recursos Humanos","153":"Ventas \/ Comercial","154":"Administracion","155":"Arte\/Diseno\/Medios","156":"Asistente administrativo","157":"Economia \/ Contabilidad","158":"Hoteleria Turismo y Gastronomia","159":"Informatica \/ Telecomunicaciones","160":"Logistica \/ Distribucion","161":"Marketing y Publicidad","162":"Medicina \/ Salud","163":"Operarios y no Profesionales","164":"Otros","165":"Profesionales y Tecnicos","166":"Recursos Humanos","167":"Servicios Domesticos","168":"Ventas \/ Comercial","169":"Medicina \/ Salud","170":"Operarios y no Profesionales","171":"Otros","172":"Profesionales y Tecnicos","173":"Ventas \/ Comercial","174":"Hoteleria Turismo y Gastronomia","175":"Operarios y no Profesionales","176":"Economia \/ Contabilidad","177":"Otros","178":"Profesionales y Tecnicos","179":"Medicina \/ Salud","180":"Operarios y no Profesionales","181":"Ventas \/ Comercial","182":"Operarios y no Profesionales","183":"Administracion","184":"Operarios y no Profesionales","185":"Medicina \/ Salud","186":"Operarios y no Profesionales","187":"Profesionales y Tecnicos","188":"Seguridad","189":"Ventas \/ Comercial","190":"Administracion","191":"Medicina \/ Salud","192":"Operarios y no Profesionales","193":"Profesionales y Tecnicos","194":"Seguridad","195":"Ventas \/ Comercial","196":"Administracion","197":"Arte\/Diseno\/Medios","198":"Asistente administrativo","199":"Economia \/ Contabilidad","200":"Educacion y Psicopedagogia","201":"Hoteleria Turismo y Gastronomia","202":"Informatica \/ Telecomunicaciones","203":"Logistica \/ Distribucion","204":"Marketing y Publicidad","205":"Medicina \/ Salud","206":"Operarios y no Profesionales","207":"Otros","208":"Profesionales y Tecnicos","209":"Recursos Humanos","210":"Servicios Domesticos","211":"Ventas \/ Comercial","212":"Administracion","213":"Arte\/Diseno\/Medios","214":"Asistente administrativo","215":"Economia \/ Contabilidad","216":"Educacion y Psicopedagogia","217":"Estetica y Cuidado Personal","218":"Hoteleria Turismo y Gastronomia","219":"Informatica \/ Telecomunicaciones","220":"Logistica \/ Distribucion","221":"Marketing y Publicidad","222":"Medicina \/ Salud","223":"Operarios y no Profesionales","224":"Otros","225":"Practicas profesionales","226":"Profesionales y Tecnicos","227":"Recepci\u00f3n \/ Secretaria","228":"Recursos Humanos","229":"Seguridad","230":"Ventas \/ Comercial","231":"Administracion","232":"Asistente administrativo","233":"Economia \/ Contabilidad","234":"Informatica \/ Telecomunicaciones","235":"Marketing y Publicidad","236":"Medicina \/ Salud","237":"Operarios y no Profesionales","238":"Otros","239":"Profesionales y Tecnicos","240":"Ventas \/ Comercial","241":"Administracion","242":"Medicina \/ Salud","243":"Recepci\u00f3n \/ Secretaria","244":"Ventas \/ Comercial","245":"Administracion","246":"Asistente administrativo","247":"Educacion y Psicopedagogia","248":"Hoteleria Turismo y Gastronomia","249":"Informatica \/ Telecomunicaciones","250":"Logistica \/ Distribucion","251":"Medicina \/ Salud","252":"Otros","253":"Profesionales y Tecnicos","254":"Recursos Humanos","255":"Ventas \/ Comercial","256":"Administracion","257":"Medicina \/ Salud","258":"Ventas \/ Comercial","259":"Economia \/ Contabilidad","260":"Medicina \/ Salud","261":"Operarios y no Profesionales","262":"Otros","263":"Profesionales y Tecnicos","264":"Recursos Humanos","265":"Ventas \/ Comercial","266":"Administracion","267":"Economia \/ Contabilidad","268":"Educacion y Psicopedagogia","269":"Logistica \/ Distribucion","270":"Ventas \/ Comercial","271":"Economia \/ Contabilidad","272":"Logistica \/ Distribucion","273":"Otros","274":"Practicas profesionales","275":"Profesionales y Tecnicos","276":"Recursos Humanos","277":"Ventas \/ Comercial","278":"Administracion","279":"Economia \/ Contabilidad","280":"Logistica \/ Distribucion","281":"Medicina \/ Salud","282":"Otros","283":"Profesionales y Tecnicos","284":"Recursos Humanos","285":"Seguridad","286":"Ventas \/ Comercial","287":"Administracion","288":"Economia \/ Contabilidad","289":"Informatica \/ Telecomunicaciones","290":"Logistica \/ Distribucion","291":"Medicina \/ Salud","292":"Ventas \/ Comercial","293":"Economia \/ Contabilidad","294":"Logistica \/ Distribucion","295":"Medicina \/ Salud","296":"Ventas \/ Comercial","297":"Administracion","298":"Economia \/ Contabilidad","299":"Logistica \/ Distribucion","300":"Medicina \/ Salud","301":"Operarios y no Profesionales","302":"Profesionales y Tecnicos","303":"Recursos Humanos","304":"Ventas \/ Comercial","305":"Administracion","306":"Arte\/Diseno\/Medios","307":"Asistente administrativo","308":"Economia \/ Contabilidad","309":"Educacion y Psicopedagogia","310":"Estetica y Cuidado Personal","311":"Hoteleria Turismo y Gastronomia","312":"Informatica \/ Telecomunicaciones","313":"Logistica \/ Distribucion","314":"Marketing y Publicidad","315":"Medicina \/ Salud","316":"Operarios y no Profesionales","317":"Otros","318":"Practicas profesionales","319":"Profesionales y Tecnicos","320":"Recepci\u00f3n \/ Secretaria","321":"Recursos Humanos","322":"Seguridad","323":"Servicios Domesticos","324":"Ventas \/ Comercial","325":"Administracion","326":"Asistente administrativo","327":"Economia \/ Contabilidad","328":"Logistica \/ Distribucion","329":"Medicina \/ Salud","330":"Operarios y no Profesionales","331":"Otros","332":"Profesionales y Tecnicos","333":"Seguridad","334":"Ventas \/ Comercial","335":"Administracion","336":"Arte\/Diseno\/Medios","337":"Asistente administrativo","338":"Economia \/ Contabilidad","339":"Educacion y Psicopedagogia","340":"Estetica y Cuidado Personal","341":"Hoteleria Turismo y Gastronomia","342":"Informatica \/ Telecomunicaciones","343":"Logistica \/ Distribucion","344":"Marketing y Publicidad","345":"Medicina \/ Salud","346":"Operarios y no Profesionales","347":"Otros","348":"Practicas profesionales","349":"Profesionales y Tecnicos","350":"Recursos Humanos","351":"Seguridad","352":"Ventas \/ Comercial","353":"Administracion","354":"Economia \/ Contabilidad","355":"Hoteleria Turismo y Gastronomia","356":"Logistica \/ Distribucion","357":"Medicina \/ Salud","358":"Operarios y no Profesionales","359":"Ventas \/ Comercial","360":"Administracion","361":"Asistente administrativo","362":"Economia \/ Contabilidad","363":"Logistica \/ Distribucion","364":"Medicina \/ Salud","365":"Operarios y no Profesionales","366":"Otros","367":"Profesionales y Tecnicos","368":"Seguridad","369":"Ventas \/ Comercial","370":"Economia \/ Contabilidad","371":"Logistica \/ Distribucion","372":"Medicina \/ Salud","373":"Operarios y no Profesionales","374":"Ventas \/ Comercial","375":"Administracion","376":"Arte\/Diseno\/Medios","377":"Asistente administrativo","378":"Economia \/ Contabilidad","379":"Educacion y Psicopedagogia","380":"Estetica y Cuidado Personal","381":"Hoteleria Turismo y Gastronomia","382":"Informatica \/ Telecomunicaciones","383":"Logistica \/ Distribucion","384":"Marketing y Publicidad","385":"Medicina \/ Salud","386":"Operarios y no Profesionales","387":"Otros","388":"Practicas profesionales","389":"Profesionales y Tecnicos","390":"Recepci\u00f3n \/ Secretaria","391":"Recursos Humanos","392":"Seguridad","393":"Servicios Domesticos","394":"Ventas \/ Comercial","395":"TodasLasCategorias","396":"TodasLasCategorias","397":"TodasLasCategorias","398":"TodasLasCategorias","399":"TodasLasCategorias","400":"TodasLasCategorias","401":"TodasLasCategorias","402":"TodasLasCategorias","403":"TodasLasCategorias","404":"TodasLasCategorias","405":"TodasLasCategorias","406":"TodasLasCategorias","407":"TodasLasCategorias","408":"TodasLasCategorias","409":"TodasLasCategorias","410":"TodasLasCategorias","411":"TodasLasCategorias","412":"TodasLasCategorias","413":"TodasLasCategorias","414":"TodasLasCategorias","415":"TodasLasCategorias","416":"TodasLasCategorias","417":"TodasLasCategorias","418":"TodasLasCategorias","419":"TodasLasCategorias","420":"TodasLasCategorias","421":"TodasLasCategorias","422":"TodasLasCategorias","423":"TodasLasCategorias","424":"TodasLasCategorias","425":"TodasLasCategorias","426":"TodasLasCategorias","427":"TodasLasCategorias","428":"TodasLasCategorias","429":"TodasLasCategorias","430":"TodasLasCategorias","431":"TodasLasCategorias","432":"TodasLasCategorias","433":"TodasLasCategorias","434":"TodasLasCategorias","435":"TodasLasCategorias","436":"TodasLasCategorias","437":"TodasLasCategorias"},"FechaDato":{"0":20200810,"1":20200810,"2":20200810,"3":20200810,"4":20200810,"5":20200810,"6":20200810,"7":20200810,"8":20200810,"9":20200810,"10":20200810,"11":20200810,"12":20200810,"13":20200810,"14":20200810,"15":20200810,"16":20200810,"17":20200810,"18":20200810,"19":20200810,"20":20200810,"21":20200810,"22":20200810,"23":20200810,"24":20200810,"25":20200810,"26":20200810,"27":20200810,"28":20200810,"29":20200810,"30":20200810,"31":20200810,"32":20200810,"33":20200810,"34":20200810,"35":20200810,"36":20200810,"37":20200810,"38":20200810,"39":20200810,"40":20200810,"41":20200810,"42":20200810,"43":20200810,"44":20200810,"45":20200810,"46":20200810,"47":20200810,"48":20200810,"49":20200810,"50":20200810,"51":20200810,"52":20200810,"53":20200810,"54":20200810,"55":20200810,"56":20200810,"57":20200810,"58":20200810,"59":20200810,"60":20200810,"61":20200810,"62":20200810,"63":20200810,"64":20200810,"65":20200810,"66":20200810,"67":20200810,"68":20200810,"69":20200810,"70":20200810,"71":20200810,"72":20200810,"73":20200810,"74":20200810,"75":20200810,"76":20200810,"77":20200810,"78":20200810,"79":20200810,"80":20200810,"81":20200810,"82":20200810,"83":20200810,"84":20200810,"85":20200810,"86":20200810,"87":20200810,"88":20200810,"89":20200810,"90":20200810,"91":20200810,"92":20200810,"93":20200810,"94":20200810,"95":20200810,"96":20200810,"97":20200810,"98":20200810,"99":20200810,"100":20200810,"101":20200810,"102":20200810,"103":20200810,"104":20200810,"105":20200810,"106":20200810,"107":20200810,"108":20200810,"109":20200810,"110":20200810,"111":20200810,"112":20200810,"113":20200810,"114":20200810,"115":20200810,"116":20200810,"117":20200810,"118":20200810,"119":20200810,"120":20200810,"121":20200810,"122":20200810,"123":20200810,"124":20200810,"125":20200810,"126":20200810,"127":20200810,"128":20200810,"129":20200810,"130":20200810,"131":20200810,"132":20200810,"133":20200810,"134":20200810,"135":20200810,"136":20200810,"137":20200810,"138":20200810,"139":20200810,"140":20200810,"141":20200810,"142":20200810,"143":20200810,"144":20200810,"145":20200810,"146":20200810,"147":20200810,"148":20200810,"149":20200810,"150":20200810,"151":20200810,"152":20200810,"153":20200810,"154":20200810,"155":20200810,"156":20200810,"157":20200810,"158":20200810,"159":20200810,"160":20200810,"161":20200810,"162":20200810,"163":20200810,"164":20200810,"165":20200810,"166":20200810,"167":20200810,"168":20200810,"169":20200810,"170":20200810,"171":20200810,"172":20200810,"173":20200810,"174":20200810,"175":20200810,"176":20200810,"177":20200810,"178":20200810,"179":20200810,"180":20200810,"181":20200810,"182":20200810,"183":20200810,"184":20200810,"185":20200810,"186":20200810,"187":20200810,"188":20200810,"189":20200810,"190":20200810,"191":20200810,"192":20200810,"193":20200810,"194":20200810,"195":20200810,"196":20200810,"197":20200810,"198":20200810,"199":20200810,"200":20200810,"201":20200810,"202":20200810,"203":20200810,"204":20200810,"205":20200810,"206":20200810,"207":20200810,"208":20200810,"209":20200810,"210":20200810,"211":20200810,"212":20200810,"213":20200810,"214":20200810,"215":20200810,"216":20200810,"217":20200810,"218":20200810,"219":20200810,"220":20200810,"221":20200810,"222":20200810,"223":20200810,"224":20200810,"225":20200810,"226":20200810,"227":20200810,"228":20200810,"229":20200810,"230":20200810,"231":20200810,"232":20200810,"233":20200810,"234":20200810,"235":20200810,"236":20200810,"237":20200810,"238":20200810,"239":20200810,"240":20200810,"241":20200810,"242":20200810,"243":20200810,"244":20200810,"245":20200810,"246":20200810,"247":20200810,"248":20200810,"249":20200810,"250":20200810,"251":20200810,"252":20200810,"253":20200810,"254":20200810,"255":20200810,"256":20200810,"257":20200810,"258":20200810,"259":20200810,"260":20200810,"261":20200810,"262":20200810,"263":20200810,"264":20200810,"265":20200810,"266":20200810,"267":20200810,"268":20200810,"269":20200810,"270":20200810,"271":20200810,"272":20200810,"273":20200810,"274":20200810,"275":20200810,"276":20200810,"277":20200810,"278":20200810,"279":20200810,"280":20200810,"281":20200810,"282":20200810,"283":20200810,"284":20200810,"285":20200810,"286":20200810,"287":20200810,"288":20200810,"289":20200810,"290":20200810,"291":20200810,"292":20200810,"293":20200810,"294":20200810,"295":20200810,"296":20200810,"297":20200810,"298":20200810,"299":20200810,"300":20200810,"301":20200810,"302":20200810,"303":20200810,"304":20200810,"305":20200810,"306":20200810,"307":20200810,"308":20200810,"309":20200810,"310":20200810,"311":20200810,"312":20200810,"313":20200810,"314":20200810,"315":20200810,"316":20200810,"317":20200810,"318":20200810,"319":20200810,"320":20200810,"321":20200810,"322":20200810,"323":20200810,"324":20200810,"325":20200810,"326":20200810,"327":20200810,"328":20200810,"329":20200810,"330":20200810,"331":20200810,"332":20200810,"333":20200810,"334":20200810,"335":20200810,"336":20200810,"337":20200810,"338":20200810,"339":20200810,"340":20200810,"341":20200810,"342":20200810,"343":20200810,"344":20200810,"345":20200810,"346":20200810,"347":20200810,"348":20200810,"349":20200810,"350":20200810,"351":20200810,"352":20200810,"353":20200810,"354":20200810,"355":20200810,"356":20200810,"357":20200810,"358":20200810,"359":20200810,"360":20200810,"361":20200810,"362":20200810,"363":20200810,"364":20200810,"365":20200810,"366":20200810,"367":20200810,"368":20200810,"369":20200810,"370":20200810,"371":20200810,"372":20200810,"373":20200810,"374":20200810,"375":20200810,"376":20200810,"377":20200810,"378":20200810,"379":20200810,"380":20200810,"381":20200810,"382":20200810,"383":20200810,"384":20200810,"385":20200810,"386":20200810,"387":20200810,"388":20200810,"389":20200810,"390":20200810,"391":20200810,"392":20200810,"393":20200810,"394":20200810,"395":20200810,"396":20200810,"397":20200810,"398":20200810,"399":20200810,"400":20200810,"401":20200810,"402":20200810,"403":20200810,"404":20200810,"405":20200810,"406":20200810,"407":20200810,"408":20200810,"409":20200810,"410":20200810,"411":20200810,"412":20200810,"413":20200810,"414":20200810,"415":20200810,"416":20200810,"417":20200810,"418":20200810,"419":20200810,"420":20200810,"421":20200810,"422":20200810,"423":20200810,"424":20200810,"425":20200810,"426":20200810,"427":20200810,"428":20200810,"429":20200810,"430":20200810,"431":20200810,"432":20200810,"433":20200810,"434":20200810,"435":20200810,"436":20200810,"437":20200810},"Count":{"0":2,"1":1,"2":1,"3":1,"4":8,"5":1,"6":3,"7":1,"8":1,"9":2,"10":1,"11":2,"12":4,"13":4,"14":1,"15":2,"16":3,"17":7,"18":7,"19":3,"20":10,"21":1,"22":4,"23":1,"24":1,"25":1,"26":4,"27":6,"28":5,"29":1,"30":12,"31":1,"32":4,"33":6,"34":13,"35":2,"36":1,"37":1,"38":1,"39":1,"40":2,"41":1,"42":5,"43":2,"44":3,"45":1,"46":3,"47":1,"48":9,"49":2,"50":1,"51":1,"52":1,"53":4,"54":4,"55":1,"56":1,"57":9,"58":1,"59":3,"60":15,"61":1,"62":2,"63":17,"64":16,"65":2,"66":3,"67":68,"68":1,"69":1,"70":6,"71":36,"72":67,"73":1,"74":174,"75":18,"76":24,"77":1,"78":33,"79":5,"80":6,"81":6,"82":54,"83":2,"84":1,"85":5,"86":19,"87":1,"88":2,"89":1,"90":13,"91":18,"92":1,"93":4,"94":89,"95":29,"96":1,"97":1,"98":37,"99":29,"100":15,"101":52,"102":6,"103":14,"104":2,"105":42,"106":9,"107":3,"108":291,"109":1,"110":1,"111":1,"112":1,"113":1,"114":1,"115":1,"116":5,"117":19,"118":16,"119":1,"120":5,"121":1,"122":29,"123":3,"124":1,"125":1,"126":1,"127":8,"128":1,"129":1,"130":1,"131":1,"132":3,"133":3,"134":1,"135":2,"136":2,"137":1,"138":1,"139":2,"140":1,"141":1,"142":1,"143":1,"144":1,"145":2,"146":1,"147":1,"148":1,"149":1,"150":1,"151":2,"152":1,"153":1,"154":2,"155":1,"156":2,"157":3,"158":1,"159":7,"160":3,"161":3,"162":5,"163":12,"164":6,"165":10,"166":1,"167":1,"168":12,"169":1,"170":1,"171":1,"172":1,"173":2,"174":1,"175":1,"176":2,"177":3,"178":1,"179":1,"180":1,"181":1,"182":1,"183":1,"184":1,"185":1,"186":1,"187":1,"188":1,"189":2,"190":1,"191":1,"192":3,"193":1,"194":1,"195":3,"196":3,"197":1,"198":3,"199":6,"200":1,"201":2,"202":8,"203":3,"204":3,"205":10,"206":17,"207":19,"208":22,"209":3,"210":1,"211":18,"212":49,"213":3,"214":13,"215":196,"216":31,"217":2,"218":9,"219":78,"220":169,"221":17,"222":275,"223":27,"224":43,"225":4,"226":105,"227":6,"228":18,"229":12,"230":470,"231":2,"232":1,"233":1,"234":2,"235":1,"236":9,"237":2,"238":3,"239":6,"240":1,"241":1,"242":3,"243":1,"244":3,"245":4,"246":4,"247":1,"248":2,"249":3,"250":7,"251":7,"252":5,"253":12,"254":1,"255":4,"256":1,"257":1,"258":2,"259":5,"260":6,"261":1,"262":2,"263":6,"264":1,"265":12,"266":1,"267":4,"268":1,"269":6,"270":13,"271":2,"272":1,"273":1,"274":1,"275":1,"276":1,"277":3,"278":1,"279":5,"280":2,"281":4,"282":3,"283":4,"284":1,"285":1,"286":10,"287":1,"288":2,"289":1,"290":1,"291":1,"292":4,"293":4,"294":1,"295":1,"296":9,"297":2,"298":3,"299":15,"300":1,"301":2,"302":4,"303":1,"304":18,"305":18,"306":3,"307":5,"308":71,"309":1,"310":1,"311":7,"312":43,"313":70,"314":4,"315":180,"316":31,"317":30,"318":1,"319":43,"320":5,"321":7,"322":6,"323":1,"324":66,"325":2,"326":1,"327":5,"328":19,"329":2,"330":1,"331":1,"332":4,"333":2,"334":13,"335":18,"336":1,"337":4,"338":89,"339":29,"340":1,"341":1,"342":37,"343":29,"344":15,"345":52,"346":6,"347":14,"348":2,"349":42,"350":9,"351":3,"352":293,"353":1,"354":1,"355":1,"356":1,"357":1,"358":1,"359":3,"360":1,"361":1,"362":7,"363":19,"364":16,"365":1,"366":3,"367":6,"368":1,"369":29,"370":3,"371":1,"372":2,"373":2,"374":8,"375":53,"376":4,"377":16,"378":202,"379":32,"380":2,"381":11,"382":86,"383":172,"384":20,"385":286,"386":47,"387":62,"388":4,"389":128,"390":6,"391":21,"392":13,"393":1,"394":491,"395":1,"396":1,"397":2,"398":2,"399":2,"400":2,"401":10,"402":1,"403":4,"404":1,"405":4,"406":1,"407":2,"408":6,"409":1,"410":5,"411":69,"412":4,"413":2,"414":2,"415":6,"416":2,"417":18,"418":6,"419":46,"420":3,"421":28,"422":24,"423":8,"424":25,"425":9,"426":15,"427":39,"428":522,"429":44,"430":643,"431":5,"432":78,"433":14,"434":10,"435":120,"436":1527,"437":1657}}